poja/__init__.py
poja/__main__.py
poja/core.py
poja/version.py
poja/database/__init__.py
poja/genclients/__init__.py
poja/mygit/__init__.py
poja/myos/__init__.py
poja/myrich/__init__.py
poja/sed/__init__.py
poja/sentry/__init__.py
poja/sonar/__init__.py
poja/vpcscoped/__init__.py
poja_by_tanjona-13.3.0.dist-info/LICENSE
poja_by_tanjona-13.3.0.dist-info/METADATA
poja_by_tanjona-13.3.0.dist-info/WHEEL
poja_by_tanjona-13.3.0.dist-info/top_level.txt
poja_by_tanjona-13.3.0.dist-info/RECORD
